contact_group_local/__init__.py
contact_group_local/contact_group.py
contact_group_local/contact_group_constans.py
contact_group_local-0.0.72.dist-info/METADATA
contact_group_local-0.0.72.dist-info/WHEEL
contact_group_local-0.0.72.dist-info/top_level.txt
contact_group_local-0.0.72.dist-info/RECORD
