Metadata-Version: 2.4
Name: contact-group-local
Version: 0.0.72
Summary: PyPI Package for Circles contact-group-local Python
Home-page: https://github.com/circles-zone/contact-group-local-python-package
Author: Circles
Author-email: info@circlez.ai
Classifier: Programming Language :: Python :: 3
Classifier: License :: Other/Proprietary License
Classifier: Operating System :: OS Independent
Requires-Dist: logger-local>=0.0.135
Requires-Dist: database-mysql-local>=0.0.300
Requires-Dist: python-sdk-remote>=0.0.93
Requires-Dist: group-remote>=0.0.111
Requires-Dist: group-local>=0.0.24
Requires-Dist: language-remote>=0.0.20
Requires-Dist: contact-local>=0.0.42
Dynamic: author
Dynamic: author-email
Dynamic: classifier
Dynamic: description
Dynamic: description-content-type
Dynamic: home-page
Dynamic: requires-dist
Dynamic: summary
